{"page":1,"surah":"Al-Fatihah","surahAr":"الفاتحة","juz":1,"firstVerse":"1:1","lastVerse":"1:7","lines":[{"line":2,"words":[{"t":"بِسْمِ","en":"In (the) name","type":"word","ayah":1,"key":"1:1","id":"بسم"},{"t":"ٱللَّهِ","en":"(of) Allah","type":"word","ayah":1,"key":"1:1","id":"الله"},{"t":"ٱلرَّحْمَـٰنِ","en":"the Most Gracious","type":"word","ayah":1,"key":"1:1","id":"الرحمن"},{"t":"ٱلرَّحِيمِ","en":"the Most Merciful","type":"word","ayah":1,"key":"1:1","id":"الرحيم"},{"t":"١","en":"(1)","type":"end","ayah":1,"key":"1:1","id":"١"}]},{"line":3,"words":[{"t":"ٱلْحَمْدُ","en":"All praises and thanks","type":"word","ayah":2,"key":"1:2","id":"الحمد"},{"t":"لِلَّهِ","en":"(be) to Allah","type":"word","ayah":2,"key":"1:2","id":"لله"},{"t":"رَبِّ","en":"the Lord","type":"word","ayah":2,"key":"1:2","id":"رب"},{"t":"ٱلْعَـٰلَمِينَ","en":"of the universe","type":"word","ayah":2,"key":"1:2","id":"العلمين"},{"t":"٢","en":"(2)","type":"end","ayah":2,"key":"1:2","id":"٢"}]},{"line":4,"words":[{"t":"ٱلرَّحْمَـٰنِ","en":"The Most Gracious","type":"word","ayah":3,"key":"1:3","id":"الرحمن"},{"t":"ٱلرَّحِيمِ","en":"the Most Merciful","type":"word","ayah":3,"key":"1:3","id":"الرحيم"},{"t":"٣","en":"(3)","type":"end","ayah":3,"key":"1:3","id":"٣"},{"t":"مَـٰلِكِ","en":"(The) Master","type":"word","ayah":4,"key":"1:4","id":"ملك"},{"t":"يَوْمِ","en":"(of the) Day","type":"word","ayah":4,"key":"1:4","id":"يوم"},{"t":"ٱلدِّينِ","en":"(of the) Judgment","type":"word","ayah":4,"key":"1:4","id":"الدين"},{"t":"٤","en":"(4)","type":"end","ayah":4,"key":"1:4","id":"٤"}]},{"line":5,"words":[{"t":"إِيَّاكَ","en":"You Alone","type":"word","ayah":5,"key":"1:5","id":"اياك"},{"t":"نَعْبُدُ","en":"we worship","type":"word","ayah":5,"key":"1:5","id":"نعبد"},{"t":"وَإِيَّاكَ","en":"and You Alone","type":"word","ayah":5,"key":"1:5","id":"واياك"},{"t":"نَسْتَعِينُ","en":"we ask for help","type":"word","ayah":5,"key":"1:5","id":"نستعين"},{"t":"٥","en":"(5)","type":"end","ayah":5,"key":"1:5","id":"٥"},{"t":"ٱهْدِنَا","en":"Guide us","type":"word","ayah":6,"key":"1:6","id":"اهدنا"}]},{"line":6,"words":[{"t":"ٱلصِّرَٰطَ","en":"(to) the path","type":"word","ayah":6,"key":"1:6","id":"الصرط"},{"t":"ٱلْمُسْتَقِيمَ","en":"the straight","type":"word","ayah":6,"key":"1:6","id":"المستقيم"},{"t":"٦","en":"(6)","type":"end","ayah":6,"key":"1:6","id":"٦"},{"t":"صِرَٰطَ","en":"(The) path","type":"word","ayah":7,"key":"1:7","id":"صرط"},{"t":"ٱلَّذِينَ","en":"(of) those","type":"word","ayah":7,"key":"1:7","id":"الذين"},{"t":"أَنْعَمْتَ","en":"You have bestowed (Your) Favors","type":"word","ayah":7,"key":"1:7","id":"انعمت"}]},{"line":7,"words":[{"t":"عَلَيْهِمْ","en":"on them","type":"word","ayah":7,"key":"1:7","id":"عليهم"},{"t":"غَيْرِ","en":"not (of)","type":"word","ayah":7,"key":"1:7","id":"غير"},{"t":"ٱلْمَغْضُوبِ","en":"those who earned (Your) wrath","type":"word","ayah":7,"key":"1:7","id":"المغضوب"},{"t":"عَلَيْهِمْ","en":"on themselves","type":"word","ayah":7,"key":"1:7","id":"عليهم"}]},{"line":8,"words":[{"t":"وَلَا","en":"and not","type":"word","ayah":7,"key":"1:7","id":"ولا"},{"t":"ٱلضَّآلِّينَ","en":"(of) those who go astray","type":"word","ayah":7,"key":"1:7","id":"الضالين"},{"t":"٧","en":"(7)","type":"end","ayah":7,"key":"1:7","id":"٧"}]}]}