{"page":135,"surah":"Al-An'am","surahAr":"الأنعام","juz":7,"firstVerse":"6:60","lastVerse":"6:68","lines":[{"line":1,"words":[{"t":"وَهُوَ","en":"And He","type":"word","ayah":60,"key":"6:60","id":"وهو"},{"t":"ٱلَّذِى","en":"(is) the One Who","type":"word","ayah":60,"key":"6:60","id":"الذي"},{"t":"يَتَوَفَّىٰكُم","en":"takes your (soul)","type":"word","ayah":60,"key":"6:60","id":"يتوفيكم"},{"t":"بِٱلَّيْلِ","en":"by the night","type":"word","ayah":60,"key":"6:60","id":"باليل"},{"t":"وَيَعْلَمُ","en":"and He knows","type":"word","ayah":60,"key":"6:60","id":"ويعلم"},{"t":"مَا","en":"what","type":"word","ayah":60,"key":"6:60","id":"ما"},{"t":"جَرَحْتُم","en":"you committed","type":"word","ayah":60,"key":"6:60","id":"جرحتم"},{"t":"بِٱلنَّهَارِ","en":"by the day","type":"word","ayah":60,"key":"6:60","id":"بالنهار"},{"t":"ثُمَّ","en":"Then","type":"word","ayah":60,"key":"6:60","id":"ثم"}]},{"line":2,"words":[{"t":"يَبْعَثُكُمْ","en":"He raises you up","type":"word","ayah":60,"key":"6:60","id":"يبعثكم"},{"t":"فِيهِ","en":"therein","type":"word","ayah":60,"key":"6:60","id":"فيه"},{"t":"لِيُقْضَىٰٓ","en":"so that is fulfilled","type":"word","ayah":60,"key":"6:60","id":"ليقضي"},{"t":"أَجَلٌۭ","en":"(the) term","type":"word","ayah":60,"key":"6:60","id":"اجل"},{"t":"مُّسَمًّۭى ۖ","en":"specified","type":"word","ayah":60,"key":"6:60","id":"مسمي"},{"t":"ثُمَّ","en":"Then","type":"word","ayah":60,"key":"6:60","id":"ثم"},{"t":"إِلَيْهِ","en":"to Him","type":"word","ayah":60,"key":"6:60","id":"اليه"},{"t":"مَرْجِعُكُمْ","en":"will be your return","type":"word","ayah":60,"key":"6:60","id":"مرجعكم"}]},{"line":3,"words":[{"t":"ثُمَّ","en":"then","type":"word","ayah":60,"key":"6:60","id":"ثم"},{"t":"يُنَبِّئُكُم","en":"He will inform you","type":"word","ayah":60,"key":"6:60","id":"ينبئكم"},{"t":"بِمَا","en":"about what","type":"word","ayah":60,"key":"6:60","id":"بما"},{"t":"كُنتُمْ","en":"you used to","type":"word","ayah":60,"key":"6:60","id":"كنتم"},{"t":"تَعْمَلُونَ","en":"do","type":"word","ayah":60,"key":"6:60","id":"تعملون"},{"t":"٦٠","en":"(60)","type":"end","ayah":60,"key":"6:60","id":"٦٠"},{"t":"وَهُوَ","en":"And He","type":"word","ayah":61,"key":"6:61","id":"وهو"},{"t":"ٱلْقَاهِرُ","en":"(is) the Subjugator","type":"word","ayah":61,"key":"6:61","id":"القاهر"},{"t":"فَوْقَ","en":"over","type":"word","ayah":61,"key":"6:61","id":"فوق"},{"t":"عِبَادِهِۦ ۖ","en":"His slaves","type":"word","ayah":61,"key":"6:61","id":"عباده"}]},{"line":4,"words":[{"t":"وَيُرْسِلُ","en":"and He sends","type":"word","ayah":61,"key":"6:61","id":"ويرسل"},{"t":"عَلَيْكُمْ","en":"over you","type":"word","ayah":61,"key":"6:61","id":"عليكم"},{"t":"حَفَظَةً","en":"guardians","type":"word","ayah":61,"key":"6:61","id":"حفظة"},{"t":"حَتَّىٰٓ","en":"until","type":"word","ayah":61,"key":"6:61","id":"حتي"},{"t":"إِذَا","en":"when","type":"word","ayah":61,"key":"6:61","id":"اذا"},{"t":"جَآءَ","en":"comes","type":"word","ayah":61,"key":"6:61","id":"جاء"},{"t":"أَحَدَكُمُ","en":"(to) anyone of you","type":"word","ayah":61,"key":"6:61","id":"احدكم"},{"t":"ٱلْمَوْتُ","en":"the death","type":"word","ayah":61,"key":"6:61","id":"الموت"},{"t":"تَوَفَّتْهُ","en":"take him","type":"word","ayah":61,"key":"6:61","id":"توفته"}]},{"line":5,"words":[{"t":"رُسُلُنَا","en":"Our messengers","type":"word","ayah":61,"key":"6:61","id":"رسلنا"},{"t":"وَهُمْ","en":"and they","type":"word","ayah":61,"key":"6:61","id":"وهم"},{"t":"لَا","en":"(do) not","type":"word","ayah":61,"key":"6:61","id":"لا"},{"t":"يُفَرِّطُونَ","en":"fail","type":"word","ayah":61,"key":"6:61","id":"يفرطون"},{"t":"٦١","en":"(61)","type":"end","ayah":61,"key":"6:61","id":"٦١"},{"t":"ثُمَّ","en":"Then","type":"word","ayah":62,"key":"6:62","id":"ثم"},{"t":"رُدُّوٓا۟","en":"they are returned","type":"word","ayah":62,"key":"6:62","id":"ردوا"},{"t":"إِلَى","en":"to","type":"word","ayah":62,"key":"6:62","id":"الي"},{"t":"ٱللَّهِ","en":"Allah","type":"word","ayah":62,"key":"6:62","id":"الله"},{"t":"مَوْلَىٰهُمُ","en":"their Protector ","type":"word","ayah":62,"key":"6:62","id":"موليهم"},{"t":"ٱلْحَقِّ ۚ","en":"[the] True","type":"word","ayah":62,"key":"6:62","id":"الحق"}]},{"line":6,"words":[{"t":"أَلَا","en":"Unquestionably","type":"word","ayah":62,"key":"6:62","id":"الا"},{"t":"لَهُ","en":"for Him","type":"word","ayah":62,"key":"6:62","id":"له"},{"t":"ٱلْحُكْمُ","en":"(is) the judgment","type":"word","ayah":62,"key":"6:62","id":"الحكم"},{"t":"وَهُوَ","en":"And He","type":"word","ayah":62,"key":"6:62","id":"وهو"},{"t":"أَسْرَعُ","en":"(is) swiftest","type":"word","ayah":62,"key":"6:62","id":"اسرع"},{"t":"ٱلْحَـٰسِبِينَ","en":"(of) the Reckoners","type":"word","ayah":62,"key":"6:62","id":"الحسبين"},{"t":"٦٢","en":"(62)","type":"end","ayah":62,"key":"6:62","id":"٦٢"},{"t":"قُلْ","en":"Say","type":"word","ayah":63,"key":"6:63","id":"قل"},{"t":"مَن","en":"Who","type":"word","ayah":63,"key":"6:63","id":"من"},{"t":"يُنَجِّيكُم","en":"saves you","type":"word","ayah":63,"key":"6:63","id":"ينجيكم"},{"t":"مِّن","en":"from","type":"word","ayah":63,"key":"6:63","id":"من"}]},{"line":7,"words":[{"t":"ظُلُمَـٰتِ","en":"darkness[es]","type":"word","ayah":63,"key":"6:63","id":"ظلمت"},{"t":"ٱلْبَرِّ","en":"(of) the land","type":"word","ayah":63,"key":"6:63","id":"البر"},{"t":"وَٱلْبَحْرِ","en":"and the sea","type":"word","ayah":63,"key":"6:63","id":"والبحر"},{"t":"تَدْعُونَهُۥ","en":"you call Him","type":"word","ayah":63,"key":"6:63","id":"تدعونه"},{"t":"تَضَرُّعًۭا","en":"humbly","type":"word","ayah":63,"key":"6:63","id":"تضرعا"},{"t":"وَخُفْيَةًۭ","en":"and secretly","type":"word","ayah":63,"key":"6:63","id":"وخفية"},{"t":"لَّئِنْ","en":"If","type":"word","ayah":63,"key":"6:63","id":"لئن"},{"t":"أَنجَىٰنَا","en":"He saves us","type":"word","ayah":63,"key":"6:63","id":"انجينا"},{"t":"مِنْ","en":"from","type":"word","ayah":63,"key":"6:63","id":"من"},{"t":"هَـٰذِهِۦ","en":"this","type":"word","ayah":63,"key":"6:63","id":"هذه"}]},{"line":8,"words":[{"t":"لَنَكُونَنَّ","en":"surely we will be","type":"word","ayah":63,"key":"6:63","id":"لنكونن"},{"t":"مِنَ","en":"from","type":"word","ayah":63,"key":"6:63","id":"من"},{"t":"ٱلشَّـٰكِرِينَ","en":"the grateful ones","type":"word","ayah":63,"key":"6:63","id":"الشكرين"},{"t":"٦٣","en":"(63)","type":"end","ayah":63,"key":"6:63","id":"٦٣"},{"t":"قُلِ","en":"Say","type":"word","ayah":64,"key":"6:64","id":"قل"},{"t":"ٱللَّهُ","en":"Allah","type":"word","ayah":64,"key":"6:64","id":"الله"},{"t":"يُنَجِّيكُم","en":"saves you","type":"word","ayah":64,"key":"6:64","id":"ينجيكم"},{"t":"مِّنْهَا","en":"from it","type":"word","ayah":64,"key":"6:64","id":"منها"},{"t":"وَمِن","en":"and from","type":"word","ayah":64,"key":"6:64","id":"ومن"},{"t":"كُلِّ","en":"every","type":"word","ayah":64,"key":"6:64","id":"كل"},{"t":"كَرْبٍۢ","en":"distress","type":"word","ayah":64,"key":"6:64","id":"كرب"}]},{"line":9,"words":[{"t":"ثُمَّ","en":"yet","type":"word","ayah":64,"key":"6:64","id":"ثم"},{"t":"أَنتُمْ","en":"you","type":"word","ayah":64,"key":"6:64","id":"انتم"},{"t":"تُشْرِكُونَ","en":"associate partners (with Allah)","type":"word","ayah":64,"key":"6:64","id":"تشركون"},{"t":"٦٤","en":"(64)","type":"end","ayah":64,"key":"6:64","id":"٦٤"},{"t":"قُلْ","en":"Say","type":"word","ayah":65,"key":"6:65","id":"قل"},{"t":"هُوَ","en":"He","type":"word","ayah":65,"key":"6:65","id":"هو"},{"t":"ٱلْقَادِرُ","en":"(is) All-Capable","type":"word","ayah":65,"key":"6:65","id":"القادر"},{"t":"عَلَىٰٓ","en":"[on]","type":"word","ayah":65,"key":"6:65","id":"علي"},{"t":"أَن","en":"to","type":"word","ayah":65,"key":"6:65","id":"ان"},{"t":"يَبْعَثَ","en":"send","type":"word","ayah":65,"key":"6:65","id":"يبعث"},{"t":"عَلَيْكُمْ","en":"upon you","type":"word","ayah":65,"key":"6:65","id":"عليكم"},{"t":"عَذَابًۭا","en":"punishment","type":"word","ayah":65,"key":"6:65","id":"عذابا"}]},{"line":10,"words":[{"t":"مِّن","en":"from","type":"word","ayah":65,"key":"6:65","id":"من"},{"t":"فَوْقِكُمْ","en":"above you","type":"word","ayah":65,"key":"6:65","id":"فوقكم"},{"t":"أَوْ","en":"or","type":"word","ayah":65,"key":"6:65","id":"او"},{"t":"مِن","en":"from","type":"word","ayah":65,"key":"6:65","id":"من"},{"t":"تَحْتِ","en":"beneath","type":"word","ayah":65,"key":"6:65","id":"تحت"},{"t":"أَرْجُلِكُمْ","en":"your feet","type":"word","ayah":65,"key":"6:65","id":"ارجلكم"},{"t":"أَوْ","en":"or","type":"word","ayah":65,"key":"6:65","id":"او"},{"t":"يَلْبِسَكُمْ","en":"(to) confuse you","type":"word","ayah":65,"key":"6:65","id":"يلبسكم"},{"t":"شِيَعًۭا","en":"(into) sects","type":"word","ayah":65,"key":"6:65","id":"شيعا"},{"t":"وَيُذِيقَ","en":"and make (you) taste ","type":"word","ayah":65,"key":"6:65","id":"ويذيق"},{"t":"بَعْضَكُم","en":"some of you","type":"word","ayah":65,"key":"6:65","id":"بعضكم"}]},{"line":11,"words":[{"t":"بَأْسَ","en":"violence","type":"word","ayah":65,"key":"6:65","id":"باس"},{"t":"بَعْضٍ ۗ","en":"(of) others","type":"word","ayah":65,"key":"6:65","id":"بعض"},{"t":"ٱنظُرْ","en":"See","type":"word","ayah":65,"key":"6:65","id":"انظر"},{"t":"كَيْفَ","en":"how","type":"word","ayah":65,"key":"6:65","id":"كيف"},{"t":"نُصَرِّفُ","en":"We explain","type":"word","ayah":65,"key":"6:65","id":"نصرف"},{"t":"ٱلْـَٔايَـٰتِ","en":"the Signs","type":"word","ayah":65,"key":"6:65","id":"الايت"},{"t":"لَعَلَّهُمْ","en":"so that they may","type":"word","ayah":65,"key":"6:65","id":"لعلهم"},{"t":"يَفْقَهُونَ","en":"understand","type":"word","ayah":65,"key":"6:65","id":"يفقهون"},{"t":"٦٥","en":"(65)","type":"end","ayah":65,"key":"6:65","id":"٦٥"}]},{"line":12,"words":[{"t":"وَكَذَّبَ","en":"But denied","type":"word","ayah":66,"key":"6:66","id":"وكذب"},{"t":"بِهِۦ","en":"it ","type":"word","ayah":66,"key":"6:66","id":"به"},{"t":"قَوْمُكَ","en":"your people","type":"word","ayah":66,"key":"6:66","id":"قومك"},{"t":"وَهُوَ","en":"while it","type":"word","ayah":66,"key":"6:66","id":"وهو"},{"t":"ٱلْحَقُّ ۚ","en":"(is) the truth","type":"word","ayah":66,"key":"6:66","id":"الحق"},{"t":"قُل","en":"Say","type":"word","ayah":66,"key":"6:66","id":"قل"},{"t":"لَّسْتُ","en":"I am not","type":"word","ayah":66,"key":"6:66","id":"لست"},{"t":"عَلَيْكُم","en":"over you","type":"word","ayah":66,"key":"6:66","id":"عليكم"},{"t":"بِوَكِيلٍۢ","en":"a manager","type":"word","ayah":66,"key":"6:66","id":"بوكيل"},{"t":"٦٦","en":"(66)","type":"end","ayah":66,"key":"6:66","id":"٦٦"},{"t":"لِّكُلِّ","en":"For every","type":"word","ayah":67,"key":"6:67","id":"لكل"}]},{"line":13,"words":[{"t":"نَبَإٍۢ","en":"news","type":"word","ayah":67,"key":"6:67","id":"نبا"},{"t":"مُّسْتَقَرٌّۭ ۚ","en":"(is) a fixed time","type":"word","ayah":67,"key":"6:67","id":"مستقر"},{"t":"وَسَوْفَ","en":"and soon","type":"word","ayah":67,"key":"6:67","id":"وسوف"},{"t":"تَعْلَمُونَ","en":"you will know","type":"word","ayah":67,"key":"6:67","id":"تعلمون"},{"t":"٦٧","en":"(67)","type":"end","ayah":67,"key":"6:67","id":"٦٧"},{"t":"وَإِذَا","en":"And when","type":"word","ayah":68,"key":"6:68","id":"واذا"},{"t":"رَأَيْتَ","en":"you see","type":"word","ayah":68,"key":"6:68","id":"رايت"},{"t":"ٱلَّذِينَ","en":"those who","type":"word","ayah":68,"key":"6:68","id":"الذين"},{"t":"يَخُوضُونَ","en":"engage (in vain talks)","type":"word","ayah":68,"key":"6:68","id":"يخوضون"},{"t":"فِىٓ","en":"about","type":"word","ayah":68,"key":"6:68","id":"في"}]},{"line":14,"words":[{"t":"ءَايَـٰتِنَا","en":"Our Verses","type":"word","ayah":68,"key":"6:68","id":"ءايتنا"},{"t":"فَأَعْرِضْ","en":"then turn away","type":"word","ayah":68,"key":"6:68","id":"فاعرض"},{"t":"عَنْهُمْ","en":"from them","type":"word","ayah":68,"key":"6:68","id":"عنهم"},{"t":"حَتَّىٰ","en":"until","type":"word","ayah":68,"key":"6:68","id":"حتي"},{"t":"يَخُوضُوا۟","en":"they engage","type":"word","ayah":68,"key":"6:68","id":"يخوضوا"},{"t":"فِى","en":"in","type":"word","ayah":68,"key":"6:68","id":"في"},{"t":"حَدِيثٍ","en":"a talk","type":"word","ayah":68,"key":"6:68","id":"حديث"},{"t":"غَيْرِهِۦ ۚ","en":"other than it","type":"word","ayah":68,"key":"6:68","id":"غيره"},{"t":"وَإِمَّا","en":"And if","type":"word","ayah":68,"key":"6:68","id":"واما"},{"t":"يُنسِيَنَّكَ","en":"causes you to forget","type":"word","ayah":68,"key":"6:68","id":"ينسينك"}]},{"line":15,"words":[{"t":"ٱلشَّيْطَـٰنُ","en":"the Shaitaan","type":"word","ayah":68,"key":"6:68","id":"الشيطن"},{"t":"فَلَا","en":"then (do) not","type":"word","ayah":68,"key":"6:68","id":"فلا"},{"t":"تَقْعُدْ","en":"sit","type":"word","ayah":68,"key":"6:68","id":"تقعد"},{"t":"بَعْدَ","en":"after","type":"word","ayah":68,"key":"6:68","id":"بعد"},{"t":"ٱلذِّكْرَىٰ","en":"the reminder","type":"word","ayah":68,"key":"6:68","id":"الذكري"},{"t":"مَعَ","en":"with","type":"word","ayah":68,"key":"6:68","id":"مع"},{"t":"ٱلْقَوْمِ","en":"the people ","type":"word","ayah":68,"key":"6:68","id":"القوم"},{"t":"ٱلظَّـٰلِمِينَ","en":"the wrongdoers","type":"word","ayah":68,"key":"6:68","id":"الظلمين"},{"t":"٦٨","en":"(68)","type":"end","ayah":68,"key":"6:68","id":"٦٨"}]}]}