{"page":214,"surah":"Yunus","surahAr":"يونس","juz":11,"firstVerse":"10:43","lastVerse":"10:53","lines":[{"line":1,"words":[{"t":"وَمِنْهُم","en":"And among them","type":"word","ayah":43,"key":"10:43","id":"ومنهم"},{"t":"مَّن","en":"(are some) who","type":"word","ayah":43,"key":"10:43","id":"من"},{"t":"يَنظُرُ","en":"look","type":"word","ayah":43,"key":"10:43","id":"ينظر"},{"t":"إِلَيْكَ ۚ","en":"at you","type":"word","ayah":43,"key":"10:43","id":"اليك"},{"t":"أَفَأَنتَ","en":"But (can) you","type":"word","ayah":43,"key":"10:43","id":"افانت"},{"t":"تَهْدِى","en":"guide","type":"word","ayah":43,"key":"10:43","id":"تهدي"},{"t":"ٱلْعُمْىَ","en":"the blind","type":"word","ayah":43,"key":"10:43","id":"العمي"},{"t":"وَلَوْ","en":"even though","type":"word","ayah":43,"key":"10:43","id":"ولو"},{"t":"كَانُوا۟","en":"they [were]","type":"word","ayah":43,"key":"10:43","id":"كانوا"}]},{"line":2,"words":[{"t":"لَا","en":"(do) not","type":"word","ayah":43,"key":"10:43","id":"لا"},{"t":"يُبْصِرُونَ","en":"see","type":"word","ayah":43,"key":"10:43","id":"يبصرون"},{"t":"٤٣","en":"(43)","type":"end","ayah":43,"key":"10:43","id":"٤٣"},{"t":"إِنَّ","en":"Indeed","type":"word","ayah":44,"key":"10:44","id":"ان"},{"t":"ٱللَّهَ","en":"Allah","type":"word","ayah":44,"key":"10:44","id":"الله"},{"t":"لَا","en":"(does) not","type":"word","ayah":44,"key":"10:44","id":"لا"},{"t":"يَظْلِمُ","en":"wrong","type":"word","ayah":44,"key":"10:44","id":"يظلم"},{"t":"ٱلنَّاسَ","en":"the people","type":"word","ayah":44,"key":"10:44","id":"الناس"},{"t":"شَيْـًۭٔا","en":"(in) anything","type":"word","ayah":44,"key":"10:44","id":"شيا"},{"t":"وَلَـٰكِنَّ","en":"but","type":"word","ayah":44,"key":"10:44","id":"ولكن"}]},{"line":3,"words":[{"t":"ٱلنَّاسَ","en":"the people","type":"word","ayah":44,"key":"10:44","id":"الناس"},{"t":"أَنفُسَهُمْ","en":"wrong themselves","type":"word","ayah":44,"key":"10:44","id":"انفسهم"},{"t":"يَظْلِمُونَ","en":"wrong themselves","type":"word","ayah":44,"key":"10:44","id":"يظلمون"},{"t":"٤٤","en":"(44)","type":"end","ayah":44,"key":"10:44","id":"٤٤"},{"t":"وَيَوْمَ","en":"And the Day","type":"word","ayah":45,"key":"10:45","id":"ويوم"},{"t":"يَحْشُرُهُمْ","en":"He will gather them","type":"word","ayah":45,"key":"10:45","id":"يحشرهم"},{"t":"كَأَن","en":"as if","type":"word","ayah":45,"key":"10:45","id":"كان"},{"t":"لَّمْ","en":"they had not remained","type":"word","ayah":45,"key":"10:45","id":"لم"},{"t":"يَلْبَثُوٓا۟","en":"they had not remained","type":"word","ayah":45,"key":"10:45","id":"يلبثوا"},{"t":"إِلَّا","en":"except","type":"word","ayah":45,"key":"10:45","id":"الا"}]},{"line":4,"words":[{"t":"سَاعَةًۭ","en":"an hour","type":"word","ayah":45,"key":"10:45","id":"ساعة"},{"t":"مِّنَ","en":"of","type":"word","ayah":45,"key":"10:45","id":"من"},{"t":"ٱلنَّهَارِ","en":"the day","type":"word","ayah":45,"key":"10:45","id":"النهار"},{"t":"يَتَعَارَفُونَ","en":"they will recognize each other","type":"word","ayah":45,"key":"10:45","id":"يتعارفون"},{"t":"بَيْنَهُمْ ۚ","en":"between them","type":"word","ayah":45,"key":"10:45","id":"بينهم"},{"t":"قَدْ","en":"Certainly","type":"word","ayah":45,"key":"10:45","id":"قد"},{"t":"خَسِرَ","en":"(will have) lost","type":"word","ayah":45,"key":"10:45","id":"خسر"},{"t":"ٱلَّذِينَ","en":"those who","type":"word","ayah":45,"key":"10:45","id":"الذين"},{"t":"كَذَّبُوا۟","en":"denied","type":"word","ayah":45,"key":"10:45","id":"كذبوا"},{"t":"بِلِقَآءِ","en":"the meeting","type":"word","ayah":45,"key":"10:45","id":"بلقاء"},{"t":"ٱللَّهِ","en":"(with) Allah","type":"word","ayah":45,"key":"10:45","id":"الله"}]},{"line":5,"words":[{"t":"وَمَا","en":"and not","type":"word","ayah":45,"key":"10:45","id":"وما"},{"t":"كَانُوا۟","en":"they were","type":"word","ayah":45,"key":"10:45","id":"كانوا"},{"t":"مُهْتَدِينَ","en":"the guided ones","type":"word","ayah":45,"key":"10:45","id":"مهتدين"},{"t":"٤٥","en":"(45)","type":"end","ayah":45,"key":"10:45","id":"٤٥"},{"t":"وَإِمَّا","en":"And whether","type":"word","ayah":46,"key":"10:46","id":"واما"},{"t":"نُرِيَنَّكَ","en":"We show you","type":"word","ayah":46,"key":"10:46","id":"نرينك"},{"t":"بَعْضَ","en":"some","type":"word","ayah":46,"key":"10:46","id":"بعض"},{"t":"ٱلَّذِى","en":"(of) that which","type":"word","ayah":46,"key":"10:46","id":"الذي"},{"t":"نَعِدُهُمْ","en":"We promised them","type":"word","ayah":46,"key":"10:46","id":"نعدهم"},{"t":"أَوْ","en":"or","type":"word","ayah":46,"key":"10:46","id":"او"},{"t":"نَتَوَفَّيَنَّكَ","en":"We cause you to die","type":"word","ayah":46,"key":"10:46","id":"نتوفينك"}]},{"line":6,"words":[{"t":"فَإِلَيْنَا","en":"then to Us","type":"word","ayah":46,"key":"10:46","id":"فالينا"},{"t":"مَرْجِعُهُمْ","en":"(is) their return","type":"word","ayah":46,"key":"10:46","id":"مرجعهم"},{"t":"ثُمَّ","en":"then","type":"word","ayah":46,"key":"10:46","id":"ثم"},{"t":"ٱللَّهُ","en":"Allah","type":"word","ayah":46,"key":"10:46","id":"الله"},{"t":"شَهِيدٌ","en":"(is) a Witness","type":"word","ayah":46,"key":"10:46","id":"شهيد"},{"t":"عَلَىٰ","en":"over","type":"word","ayah":46,"key":"10:46","id":"علي"},{"t":"مَا","en":"what","type":"word","ayah":46,"key":"10:46","id":"ما"},{"t":"يَفْعَلُونَ","en":"they do","type":"word","ayah":46,"key":"10:46","id":"يفعلون"},{"t":"٤٦","en":"(46)","type":"end","ayah":46,"key":"10:46","id":"٤٦"},{"t":"وَلِكُلِّ","en":"And for every","type":"word","ayah":47,"key":"10:47","id":"ولكل"}]},{"line":7,"words":[{"t":"أُمَّةٍۢ","en":"nation","type":"word","ayah":47,"key":"10:47","id":"امة"},{"t":"رَّسُولٌۭ ۖ","en":"(is) a Messenger","type":"word","ayah":47,"key":"10:47","id":"رسول"},{"t":"فَإِذَا","en":"So when","type":"word","ayah":47,"key":"10:47","id":"فاذا"},{"t":"جَآءَ","en":"comes","type":"word","ayah":47,"key":"10:47","id":"جاء"},{"t":"رَسُولُهُمْ","en":"their Messenger","type":"word","ayah":47,"key":"10:47","id":"رسولهم"},{"t":"قُضِىَ","en":"it will be judged","type":"word","ayah":47,"key":"10:47","id":"قضي"},{"t":"بَيْنَهُم","en":"between them","type":"word","ayah":47,"key":"10:47","id":"بينهم"},{"t":"بِٱلْقِسْطِ","en":"in justice","type":"word","ayah":47,"key":"10:47","id":"بالقسط"},{"t":"وَهُمْ","en":"and they","type":"word","ayah":47,"key":"10:47","id":"وهم"}]},{"line":8,"words":[{"t":"لَا","en":"(will) not","type":"word","ayah":47,"key":"10:47","id":"لا"},{"t":"يُظْلَمُونَ","en":"be wronged","type":"word","ayah":47,"key":"10:47","id":"يظلمون"},{"t":"٤٧","en":"(47)","type":"end","ayah":47,"key":"10:47","id":"٤٧"},{"t":"وَيَقُولُونَ","en":"And they say","type":"word","ayah":48,"key":"10:48","id":"ويقولون"},{"t":"مَتَىٰ","en":"When","type":"word","ayah":48,"key":"10:48","id":"متي"},{"t":"هَـٰذَا","en":"(will) this","type":"word","ayah":48,"key":"10:48","id":"هذا"},{"t":"ٱلْوَعْدُ","en":"the promise (be fulfilled)","type":"word","ayah":48,"key":"10:48","id":"الوعد"},{"t":"إِن","en":"if","type":"word","ayah":48,"key":"10:48","id":"ان"},{"t":"كُنتُمْ","en":"you are","type":"word","ayah":48,"key":"10:48","id":"كنتم"},{"t":"صَـٰدِقِينَ","en":"truthful","type":"word","ayah":48,"key":"10:48","id":"صدقين"}]},{"line":9,"words":[{"t":"٤٨","en":"(48)","type":"end","ayah":48,"key":"10:48","id":"٤٨"},{"t":"قُل","en":"Say","type":"word","ayah":49,"key":"10:49","id":"قل"},{"t":"لَّآ","en":"Not","type":"word","ayah":49,"key":"10:49","id":"لا"},{"t":"أَمْلِكُ","en":"I have power","type":"word","ayah":49,"key":"10:49","id":"املك"},{"t":"لِنَفْسِى","en":"for myself","type":"word","ayah":49,"key":"10:49","id":"لنفسي"},{"t":"ضَرًّۭا","en":"(for) any harm","type":"word","ayah":49,"key":"10:49","id":"ضرا"},{"t":"وَلَا","en":"and not","type":"word","ayah":49,"key":"10:49","id":"ولا"},{"t":"نَفْعًا","en":"(for) any profit","type":"word","ayah":49,"key":"10:49","id":"نفعا"},{"t":"إِلَّا","en":"except","type":"word","ayah":49,"key":"10:49","id":"الا"},{"t":"مَا","en":"what","type":"word","ayah":49,"key":"10:49","id":"ما"},{"t":"شَآءَ","en":"Allah wills","type":"word","ayah":49,"key":"10:49","id":"شاء"},{"t":"ٱللَّهُ ۗ","en":"Allah wills","type":"word","ayah":49,"key":"10:49","id":"الله"},{"t":"لِكُلِّ","en":"For every","type":"word","ayah":49,"key":"10:49","id":"لكل"},{"t":"أُمَّةٍ","en":"nation","type":"word","ayah":49,"key":"10:49","id":"امة"}]},{"line":10,"words":[{"t":"أَجَلٌ ۚ","en":"(is) a term","type":"word","ayah":49,"key":"10:49","id":"اجل"},{"t":"إِذَا","en":"When","type":"word","ayah":49,"key":"10:49","id":"اذا"},{"t":"جَآءَ","en":"comes","type":"word","ayah":49,"key":"10:49","id":"جاء"},{"t":"أَجَلُهُمْ","en":"their term","type":"word","ayah":49,"key":"10:49","id":"اجلهم"},{"t":"فَلَا","en":"then not","type":"word","ayah":49,"key":"10:49","id":"فلا"},{"t":"يَسْتَـْٔخِرُونَ","en":"they remain behind","type":"word","ayah":49,"key":"10:49","id":"يستخرون"},{"t":"سَاعَةًۭ ۖ","en":"an hour","type":"word","ayah":49,"key":"10:49","id":"ساعة"},{"t":"وَلَا","en":"and not","type":"word","ayah":49,"key":"10:49","id":"ولا"},{"t":"يَسْتَقْدِمُونَ","en":"they can precede (it)","type":"word","ayah":49,"key":"10:49","id":"يستقدمون"},{"t":"٤٩","en":"(49)","type":"end","ayah":49,"key":"10:49","id":"٤٩"}]},{"line":11,"words":[{"t":"قُلْ","en":"Say","type":"word","ayah":50,"key":"10:50","id":"قل"},{"t":"أَرَءَيْتُمْ","en":"Do you see","type":"word","ayah":50,"key":"10:50","id":"ارءيتم"},{"t":"إِنْ","en":"if","type":"word","ayah":50,"key":"10:50","id":"ان"},{"t":"أَتَىٰكُمْ","en":"comes to you","type":"word","ayah":50,"key":"10:50","id":"اتيكم"},{"t":"عَذَابُهُۥ","en":"His punishment","type":"word","ayah":50,"key":"10:50","id":"عذابه"},{"t":"بَيَـٰتًا","en":"(by) night","type":"word","ayah":50,"key":"10:50","id":"بيتا"},{"t":"أَوْ","en":"or","type":"word","ayah":50,"key":"10:50","id":"او"},{"t":"نَهَارًۭا","en":"(by) day","type":"word","ayah":50,"key":"10:50","id":"نهارا"},{"t":"مَّاذَا","en":"what (portion)","type":"word","ayah":50,"key":"10:50","id":"ماذا"},{"t":"يَسْتَعْجِلُ","en":"of it would (wish to) hasten","type":"word","ayah":50,"key":"10:50","id":"يستعجل"},{"t":"مِنْهُ","en":"of it would (wish to) hasten","type":"word","ayah":50,"key":"10:50","id":"منه"}]},{"line":12,"words":[{"t":"ٱلْمُجْرِمُونَ","en":"the criminals","type":"word","ayah":50,"key":"10:50","id":"المجرمون"},{"t":"٥٠","en":"(50)","type":"end","ayah":50,"key":"10:50","id":"٥٠"},{"t":"أَثُمَّ","en":"Is (it) then","type":"word","ayah":51,"key":"10:51","id":"اثم"},{"t":"إِذَا","en":"when","type":"word","ayah":51,"key":"10:51","id":"اذا"},{"t":"مَا","en":"when","type":"word","ayah":51,"key":"10:51","id":"ما"},{"t":"وَقَعَ","en":"(it had) occurred","type":"word","ayah":51,"key":"10:51","id":"وقع"},{"t":"ءَامَنتُم","en":"you (will) believe","type":"word","ayah":51,"key":"10:51","id":"ءامنتم"},{"t":"بِهِۦٓ ۚ","en":"in it","type":"word","ayah":51,"key":"10:51","id":"به"},{"t":"ءَآلْـَٔـٰنَ","en":"Now","type":"word","ayah":51,"key":"10:51","id":"ءالن"},{"t":"وَقَدْ","en":"And certainly","type":"word","ayah":51,"key":"10:51","id":"وقد"},{"t":"كُنتُم","en":"you were","type":"word","ayah":51,"key":"10:51","id":"كنتم"},{"t":"بِهِۦ","en":"seeking to hasten it","type":"word","ayah":51,"key":"10:51","id":"به"}]},{"line":13,"words":[{"t":"تَسْتَعْجِلُونَ","en":"seeking to hasten it","type":"word","ayah":51,"key":"10:51","id":"تستعجلون"},{"t":"٥١","en":"(51)","type":"end","ayah":51,"key":"10:51","id":"٥١"},{"t":"ثُمَّ","en":"Then","type":"word","ayah":52,"key":"10:52","id":"ثم"},{"t":"قِيلَ","en":"it will be said","type":"word","ayah":52,"key":"10:52","id":"قيل"},{"t":"لِلَّذِينَ","en":"to those who","type":"word","ayah":52,"key":"10:52","id":"للذين"},{"t":"ظَلَمُوا۟","en":"wronged","type":"word","ayah":52,"key":"10:52","id":"ظلموا"},{"t":"ذُوقُوا۟","en":"Taste","type":"word","ayah":52,"key":"10:52","id":"ذوقوا"},{"t":"عَذَابَ","en":"punishment","type":"word","ayah":52,"key":"10:52","id":"عذاب"},{"t":"ٱلْخُلْدِ","en":"the everlasting","type":"word","ayah":52,"key":"10:52","id":"الخلد"}]},{"line":14,"words":[{"t":"هَلْ","en":"Are you (being) recompensed","type":"word","ayah":52,"key":"10:52","id":"هل"},{"t":"تُجْزَوْنَ","en":"Are you (being) recompensed","type":"word","ayah":52,"key":"10:52","id":"تجزون"},{"t":"إِلَّا","en":"except","type":"word","ayah":52,"key":"10:52","id":"الا"},{"t":"بِمَا","en":"for what","type":"word","ayah":52,"key":"10:52","id":"بما"},{"t":"كُنتُمْ","en":"you used (to)","type":"word","ayah":52,"key":"10:52","id":"كنتم"},{"t":"تَكْسِبُونَ","en":"earn","type":"word","ayah":52,"key":"10:52","id":"تكسبون"},{"t":"٥٢","en":"(52)","type":"end","ayah":52,"key":"10:52","id":"٥٢"},{"t":"۞ وَيَسْتَنۢبِـُٔونَكَ","en":"And they ask you to inform","type":"word","ayah":53,"key":"10:53","id":"ويستنبونك"}]},{"line":15,"words":[{"t":"أَحَقٌّ","en":"Is it true","type":"word","ayah":53,"key":"10:53","id":"احق"},{"t":"هُوَ ۖ","en":"Is it true","type":"word","ayah":53,"key":"10:53","id":"هو"},{"t":"قُلْ","en":"Say","type":"word","ayah":53,"key":"10:53","id":"قل"},{"t":"إِى","en":"Yes","type":"word","ayah":53,"key":"10:53","id":"اي"},{"t":"وَرَبِّىٓ","en":"by my Lord","type":"word","ayah":53,"key":"10:53","id":"وربي"},{"t":"إِنَّهُۥ","en":"Indeed, it","type":"word","ayah":53,"key":"10:53","id":"انه"},{"t":"لَحَقٌّۭ ۖ","en":"(is) surely the truth","type":"word","ayah":53,"key":"10:53","id":"لحق"},{"t":"وَمَآ","en":"and not","type":"word","ayah":53,"key":"10:53","id":"وما"},{"t":"أَنتُم","en":"you","type":"word","ayah":53,"key":"10:53","id":"انتم"},{"t":"بِمُعْجِزِينَ","en":"(can) escape (it)","type":"word","ayah":53,"key":"10:53","id":"بمعجزين"},{"t":"٥٣","en":"(53)","type":"end","ayah":53,"key":"10:53","id":"٥٣"}]}]}